{"cameraMode":{"drawMode":0,"name":"Shaded","section":"Shading Mode"},"sceneLighting":true,"audioPlay":false,"sceneViewState":{"m_AlwaysRefresh":false,"showFog":true,"showSkybox":false,"showFlares":true,"showImageEffects":true,"showParticleSystems":true,"showVisualEffectGraphs":true,"m_FxEnabled":true},"in2DMode":false,"pivot":{"x":-1.4251317977905274,"y":5.986992835998535,"z":-1.6676042079925538},"rotation":{"x":-0.06420399993658066,"y":0.9125955700874329,"z":-0.37193563580513,"w":-0.15761326253414155},"size":7.817167282104492,"orthographic":true}